bartlebot/production.py
bartlebot/bin/__init__.py
bartlebot/bin/bot.py
bartlebot/scenes/__init__.py
bartlebot/scenes/law_library/__init__.py
bartlebot/scenes/law_library/doc_enrichments.py
bartlebot/scenes/law_library/docs.py
bartlebot/scenes/law_library/entity_resolvers.py
bartlebot/scenes/law_library/kg.py
bartlebot/scenes/law_library/query_handler.py
bartlebot-0.0.5.dist-info/licenses/LICENSE
bartlebot-0.0.5.dist-info/METADATA
bartlebot-0.0.5.dist-info/WHEEL
bartlebot-0.0.5.dist-info/entry_points.txt
bartlebot-0.0.5.dist-info/top_level.txt
bartlebot-0.0.5.dist-info/RECORD
